<?xml version="1.0" encoding="utf-8"?>
<odoo>
    <data noupdate="1">
        
        <record id="supplier_relationship_strength_1" model="scm.supplier_relationship_strength">
            <!-- <field name="supplier_id" ref="scm.supplier"/> Reference to an existing supplier -->
            <field name="communication">4</field> <!-- Score from 1 to 5 -->
            <field name="trust">5</field> <!-- Score from 1 to 5 -->
            <field name="transparency">4</field> <!-- Score from 1 to 5 -->
            <field name="collaboration">5</field> <!-- Score from 1 to 5 -->
            <field name="delivery_rate">95.00</field> <!-- Delivery rate as a percentage -->
            <field name="relationship_score">4.6</field> <!-- Calculated relationship score -->
        </record>

        <record id="supplier_relationship_strength_2" model="scm.supplier_relationship_strength">
            <!-- <field name="supplier_id" ref="supplier2"/> Reference to another existing supplier -->
            <field name="communication">3</field> <!-- Score from 1 to 5 -->
            <field name="trust">4</field> <!-- Score from 1 to 5 -->
            <field name="transparency">3</field> <!-- Score from 1 to 5 -->
            <field name="collaboration">4</field> <!-- Score from 1 to 5 -->
            <field name="delivery_rate">90.00</field> <!-- Delivery rate as a percentage -->
            <field name="relationship_score">3.6</field> <!-- Calculated relationship score -->
        </record>

        <record id="supplier_relationship_strength_3" model="scm.supplier_relationship_strength">
            <!-- <field name="supplier_id" ref="supplier3"/> Reference to another existing supplier -->
            <field name="communication">5</field> <!-- Score from 1 to 5 -->
            <field name="trust">5</field> <!-- Score from 1 to 5 -->
            <field name="transparency">5</field> <!-- Score from 1 to 5 -->
            <field name="collaboration">5</field> <!-- Score from 1 to 5 -->
            <field name="delivery_rate">98.00</field> <!-- Delivery rate as a percentage -->
            <field name="relationship_score">5.0</field> <!-- Calculated relationship score -->
        </record>

        <record id="supplier_relationship_strength_4" model="scm.supplier_relationship_strength">
            <!-- <field name="supplier_id" ref="supplier4"/> Reference to another existing supplier -->
            <field name="communication">2</field> <!-- Score from 1 to 5 -->
            <field name="trust">3</field> <!-- Score from 1 to 5 -->
            <field name="transparency">2</field> <!-- Score from 1 to 5 -->
            <field name="collaboration">3</field> <!-- Score from 1 to 5 -->
            <field name="delivery_rate">85.00</field> <!-- Delivery rate as a percentage -->
            <field name="relationship_score">2.6</field> <!-- Calculated relationship score -->
        </record>
    </data>
</odoo>
